[{"start":30,"end":780,"word":"Novena"},{"start":780,"end":980,"word":"a"},{"start":980,"end":2000,"word":"San"},{"start":2000,"end":2000,"word":"José"},{"start":2000,"end":2660,"word":"Día"},{"start":2660,"end":3280,"word":"9"},{"start":3280,"end":4050,"word":"Patrón"},{"start":4050,"end":4220,"word":"de"},{"start":4220,"end":4430,"word":"la"},{"start":4430,"end":5200,"word":"Iglesia"},{"start":5200,"end":5440,"word":"San"},{"start":5440,"end":5850,"word":"José"},{"start":5850,"end":6010,"word":"es"},{"start":6010,"end":6560,"word":"patrón"},{"start":6560,"end":6670,"word":"de"},{"start":6670,"end":6870,"word":"la"},{"start":6870,"end":7450,"word":"Iglesia"},{"start":7450,"end":8430,"word":"universal,"},{"start":8430,"end":8530,"word":"su"},{"start":8530,"end":8980,"word":"cuidado"},{"start":8980,"end":9130,"word":"se"},{"start":9130,"end":9730,"word":"extiende"},{"start":9730,"end":9780,"word":"a"},{"start":9780,"end":10430,"word":"todos"},{"start":10430,"end":10450,"word":"los"},{"start":10450,"end":11120,"word":"fieles,"},{"start":11120,"end":11440,"word":"como"},{"start":11440,"end":11830,"word":"cuido"},{"start":11830,"end":11920,"word":"a"},{"start":11920,"end":12100,"word":"la"},{"start":12100,"end":12380,"word":"Sagrada"},{"start":12380,"end":13280,"word":"Familia,"},{"start":13280,"end":14560,"word":"oremos."},{"start":14560,"end":14830,"word":"San"},{"start":14830,"end":15540,"word":"José,"},{"start":15540,"end":15840,"word":"patrón"},{"start":15840,"end":16230,"word":"de"},{"start":16230,"end":16610,"word":"la"},{"start":16610,"end":17280,"word":"Iglesia,"},{"start":17280,"end":17880,"word":"cuida"},{"start":17880,"end":17910,"word":"de"},{"start":17910,"end":18370,"word":"todos"},{"start":18370,"end":18640,"word":"los"},{"start":18640,"end":19840,"word":"cristianos,"},{"start":19840,"end":20060,"word":"ten"},{"start":20060,"end":20470,"word":"comiendo"},{"start":20470,"end":20550,"word":"mi"},{"start":20550,"end":20800,"word":"vida"},{"start":20800,"end":20870,"word":"y"},{"start":20870,"end":21010,"word":"la"},{"start":21010,"end":21150,"word":"de"},{"start":21150,"end":21290,"word":"mi"},{"start":21290,"end":21930,"word":"familia,"},{"start":21930,"end":22130,"word":"sea"},{"start":22130,"end":22850,"word":"nuestro"},{"start":22850,"end":23290,"word":"protector"},{"start":23290,"end":24520,"word":"siempre."},{"start":24550,"end":25220,"word":"Amén,"},{"start":25220,"end":25710,"word":"Padre"},{"start":25710,"end":26630,"word":"Nuestro,"},{"start":26630,"end":26930,"word":"que"},{"start":26930,"end":27740,"word":"estás"},{"start":27740,"end":27840,"word":"en"},{"start":27840,"end":27940,"word":"el"},{"start":27940,"end":28650,"word":"cielo,"},{"start":28650,"end":29770,"word":"santificado"},{"start":29770,"end":30070,"word":"sea"},{"start":30070,"end":30270,"word":"tu"},{"start":30270,"end":31090,"word":"nombre,"},{"start":31090,"end":31330,"word":"venga"},{"start":31330,"end":31380,"word":"a"},{"start":31380,"end":31800,"word":"nosotros"},{"start":31800,"end":31970,"word":"tu"},{"start":31970,"end":32560,"word":"reino,"},{"start":32560,"end":33140,"word":"hágase"},{"start":33140,"end":33820,"word":"tu"},{"start":33820,"end":33990,"word":"voluntad"},{"start":33990,"end":34160,"word":"en"},{"start":34160,"end":34330,"word":"la"},{"start":34330,"end":35120,"word":"tierra"},{"start":35120,"end":35180,"word":"como"},{"start":35180,"end":35350,"word":"en"},{"start":35350,"end":35520,"word":"el"},{"start":35520,"end":36200,"word":"cielo,"},{"start":36200,"end":36440,"word":"danos"},{"start":36440,"end":37010,"word":"hoy"},{"start":37010,"end":37050,"word":"nuestro"},{"start":37050,"end":37200,"word":"pan"},{"start":37200,"end":37320,"word":"de"},{"start":37320,"end":37740,"word":"cada"},{"start":37740,"end":38370,"word":"día,"},{"start":38370,"end":39370,"word":"perdona"},{"start":39370,"end":39940,"word":"nuestras"},{"start":39940,"end":40920,"word":"ofensas,"},{"start":40920,"end":41100,"word":"como"},{"start":41100,"end":41460,"word":"también"},{"start":41460,"end":41830,"word":"nosotros"},{"start":41830,"end":42260,"word":"perdonamos"},{"start":42260,"end":42400,"word":"a"},{"start":42400,"end":42560,"word":"los"},{"start":42560,"end":42570,"word":"que"},{"start":42570,"end":42760,"word":"nos"},{"start":42760,"end":43630,"word":"ofenden,"},{"start":43630,"end":43820,"word":"no"},{"start":43820,"end":44100,"word":"nos"},{"start":44100,"end":44780,"word":"dejes"},{"start":44780,"end":44970,"word":"caer"},{"start":44970,"end":45160,"word":"en"},{"start":45160,"end":45350,"word":"la"},{"start":45350,"end":46330,"word":"tentación"},{"start":46330,"end":46420,"word":"y"},{"start":46420,"end":47200,"word":"libranos"},{"start":47200,"end":47480,"word":"del"},{"start":47480,"end":48200,"word":"mal."},{"start":48230,"end":48890,"word":"Amén,"},{"start":48890,"end":49310,"word":"Dios"},{"start":49310,"end":49500,"word":"te"},{"start":49500,"end":50250,"word":"salve"},{"start":50250,"end":50820,"word":"María,"},{"start":50820,"end":51520,"word":"llena"},{"start":51520,"end":51730,"word":"eres"},{"start":51730,"end":51930,"word":"de"},{"start":51930,"end":52730,"word":"gracia,"},{"start":52730,"end":53440,"word":"el"},{"start":53440,"end":53550,"word":"Señor"},{"start":53550,"end":53750,"word":"es"},{"start":53750,"end":54660,"word":"contigo,"},{"start":54660,"end":55490,"word":"bendita"},{"start":55490,"end":55640,"word":"tu"},{"start":55640,"end":55960,"word":"eres"},{"start":55960,"end":56400,"word":"entre"},{"start":56400,"end":56840,"word":"todas"},{"start":56840,"end":57100,"word":"las"},{"start":57100,"end":57980,"word":"mujeres,"},{"start":57980,"end":58010,"word":"y"},{"start":58010,"end":58580,"word":"bendito"},{"start":58580,"end":58750,"word":"es"},{"start":58750,"end":58910,"word":"el"},{"start":58910,"end":59360,"word":"fruto"},{"start":59360,"end":59530,"word":"de"},{"start":59530,"end":59700,"word":"tu"},{"start":59700,"end":60460,"word":"vientre,"},{"start":60460,"end":61240,"word":"Jesús,"},{"start":61240,"end":61620,"word":"Santa"},{"start":61620,"end":62480,"word":"María,"},{"start":62480,"end":62720,"word":"Madre"},{"start":62720,"end":62880,"word":"de"},{"start":62880,"end":63370,"word":"Dios,"},{"start":63370,"end":63770,"word":"ruega"},{"start":63770,"end":64020,"word":"por"},{"start":64020,"end":64770,"word":"nosotros"},{"start":64770,"end":65560,"word":"pecadores,"},{"start":65560,"end":66040,"word":"ahora"},{"start":66040,"end":66050,"word":"y"},{"start":66050,"end":66250,"word":"en"},{"start":66250,"end":66370,"word":"la"},{"start":66370,"end":66700,"word":"hora"},{"start":66700,"end":66860,"word":"de"},{"start":66860,"end":67930,"word":"nuestra"},{"start":67930,"end":68280,"word":"muerte."},{"start":68280,"end":69030,"word":"Amén,"},{"start":69030,"end":69660,"word":"gloria"},{"start":69660,"end":70230,"word":"al"},{"start":70230,"end":70440,"word":"Padre"},{"start":70440,"end":70550,"word":"y"},{"start":70550,"end":70770,"word":"al"},{"start":70770,"end":71160,"word":"Hijo"},{"start":71160,"end":71530,"word":"y"},{"start":71530,"end":71600,"word":"al"},{"start":71600,"end":72490,"word":"Espíritu"},{"start":72490,"end":73520,"word":"Santo,"},{"start":73520,"end":73680,"word":"como"},{"start":73680,"end":74010,"word":"era"},{"start":74010,"end":74230,"word":"en"},{"start":74230,"end":74450,"word":"el"},{"start":74450,"end":75750,"word":"principio,"},{"start":75750,"end":75920,"word":"ahora"},{"start":75920,"end":76560,"word":"y"},{"start":76560,"end":77120,"word":"siempre,"},{"start":77150,"end":77250,"word":"los"},{"start":77250,"end":77510,"word":"siglos"},{"start":77510,"end":77590,"word":"de"},{"start":77590,"end":77720,"word":"los"},{"start":77720,"end":78120,"word":"siglos."},{"start":78120,"end":78120,"word":"Amén."}]